callabletoolx.py
callabletoolx-1.0.1.dist-info/licenses/LICENSE
callabletoolx-1.0.1.dist-info/METADATA
callabletoolx-1.0.1.dist-info/WHEEL
callabletoolx-1.0.1.dist-info/top_level.txt
callabletoolx-1.0.1.dist-info/RECORD
